odoo/addons/website_oca_psc_team/README.rst
odoo/addons/website_oca_psc_team/__init__.py
odoo/addons/website_oca_psc_team/__manifest__.py
odoo/addons/website_oca_psc_team/controllers/__init__.py
odoo/addons/website_oca_psc_team/controllers/main.py
odoo/addons/website_oca_psc_team/demo/res_users.xml
odoo/addons/website_oca_psc_team/readme/CONTRIBUTORS.rst
odoo/addons/website_oca_psc_team/readme/DESCRIPTION.rst
odoo/addons/website_oca_psc_team/readme/USAGE.rst
odoo/addons/website_oca_psc_team/static/description/icon.png
odoo/addons/website_oca_psc_team/static/description/index.html
odoo/addons/website_oca_psc_team/static/src/css/website_oca_psc_team.css
odoo/addons/website_oca_psc_team/static/src/img/icon.png
odoo/addons/website_oca_psc_team/static/src/js/psc_team_tour.js
odoo/addons/website_oca_psc_team/static/src/scss/website_oca_psc_team.scss
odoo/addons/website_oca_psc_team/templates/assets.xml
odoo/addons/website_oca_psc_team/templates/psc_category_template.xml
odoo/addons/website_oca_psc_team/templates/website_oca_psc_team_data.xml
odoo/addons/website_oca_psc_team/tests/__init__.py
odoo/addons/website_oca_psc_team/tests/test_psc_team.py
odoo12_addon_website_oca_psc_team-12.0.1.1.0.dist-info/METADATA
odoo12_addon_website_oca_psc_team-12.0.1.1.0.dist-info/WHEEL
odoo12_addon_website_oca_psc_team-12.0.1.1.0.dist-info/top_level.txt
odoo12_addon_website_oca_psc_team-12.0.1.1.0.dist-info/RECORD
